MANIFEST.in
setup.cfg
setup.py
SnappEmailApiClient.egg-info/PKG-INFO
SnappEmailApiClient.egg-info/SOURCES.txt
SnappEmailApiClient.egg-info/dependency_links.txt
SnappEmailApiClient.egg-info/requires.txt
SnappEmailApiClient.egg-info/top_level.txt
generate/__init__.py
generate/generator.py
generate/iterable_names.py
snapp_email/__init__.py
snapp_email/api_client.py
snapp_email/messaging.py
snapp_email/datacontract/__init__.py
snapp_email/datacontract/classes.py
snapp_email/datacontract/content_type_to_class_mapping.py
snapp_email/datacontract/iterable_object_mappings.py
snapp_email/datacontract/mappings.py
snapp_email/datacontract/subclasses.py
snapp_email/datacontract/utils.py
snapp_email/endpoints/__init__.py
snapp_email/endpoints/_batch/BatchRequest_22Endpoint.py
snapp_email/endpoints/_batch/__init__.py
snapp_email/endpoints/_job/AsyncJobStatus_22Endpoint.py
snapp_email/endpoints/_job/__init__.py
snapp_email/endpoints/action/ActionDeleteMention_18Endpoint.py
snapp_email/endpoints/action/ActionDeletePinNotification_18Endpoint.py
snapp_email/endpoints/action/ActionDeleteQuestion_18Endpoint.py
snapp_email/endpoints/action/ActionDeleteReminder_18Endpoint.py
snapp_email/endpoints/action/ActionDelete_18Endpoint.py
snapp_email/endpoints/action/ActionFinishWorkflow_18Endpoint.py
snapp_email/endpoints/action/ActionHideStream_18Endpoint.py
snapp_email/endpoints/action/ActionNextStep_18Endpoint.py
snapp_email/endpoints/action/ActionSetReminder_18Endpoint.py
snapp_email/endpoints/action/ActionableResourceAvailability_20Endpoint.py
snapp_email/endpoints/action/ActionableResourceOverview_20Endpoint.py
snapp_email/endpoints/action/ActionableResourceOverview_21Endpoint.py
snapp_email/endpoints/action/ActionableResourceOverview_22Endpoint.py
snapp_email/endpoints/action/ActionableResource_20Endpoint.py
snapp_email/endpoints/action/ActionableResource_21Endpoint.py
snapp_email/endpoints/action/ActionableResource_22Endpoint.py
snapp_email/endpoints/action/ListOfActionableResourcesPage_20Endpoint.py
snapp_email/endpoints/action/ListOfActionableResourcesPage_21Endpoint.py
snapp_email/endpoints/action/ListOfActionableResourcesPage_22Endpoint.py
snapp_email/endpoints/action/__init__.py
