Metadata-Version: 1.1
Name: SnappEmailApiClient
Version: 0.3.38
Summary: Python API Client for Snapp Email
Home-page: https://github.com/4thOffice/ApiClient.py
Author: Snapp.Email
Author-email: info@marg.si
License: UNKNOWN
Download-URL: https://github.com/4thOffice/ApiClient.py/tarball/v0.3.38
Keywords: api,client
Platform: UNKNOWN
